COPYRIGHT
MANIFEST.in
Makefile
README
setup.cfg
setup.py
test/.test_pseudo_binary.py.swp
test/__init__.py
test/test_author_handling.py
test/test_base_href.py
test/test_compile.py
test/test_pseudo_binary.py
test/test_wikitext_render_map.py
tiddlywebplugins/__init__.py
tiddlywebplugins.atom.egg-info/PKG-INFO
tiddlywebplugins.atom.egg-info/SOURCES.txt
tiddlywebplugins.atom.egg-info/dependency_links.txt
tiddlywebplugins.atom.egg-info/namespace_packages.txt
tiddlywebplugins.atom.egg-info/not-zip-safe
tiddlywebplugins.atom.egg-info/requires.txt
tiddlywebplugins.atom.egg-info/top_level.txt
tiddlywebplugins/atom/__init__.py
tiddlywebplugins/atom/feed.py
tiddlywebplugins/atom/htmllinks.py