Metadata-Version: 1.0
Name: tiddlywebplugins.atom
Version: 1.4.3
Summary: A TiddlyWeb plugin that provides an Atom feed of tiddler collections.
Home-page: http://pypi.python.org/pypi/tiddlywebplugins.atom
Author: Chris Dent
Author-email: cdent@peermore.com
License: BSD
Platform: Posix; MacOS X; Windows
